logloglog/__init__.py
logloglog/__main__.py
logloglog/cache.py
logloglog/line_index.py
logloglog/log_file.py
logloglog/logloglog.py
logloglog/widthview.py
logloglog/tools/__init__.py
logloglog/tools/stream_logs.py
logloglog/ui/__init__.py
logloglog/ui/textual/__init__.py
logloglog/ui/textual/log_widget.py
logloglog-0.0.1.dist-info/entry_points.txt
logloglog-0.0.1.dist-info/licenses/LICENSE.md
logloglog-0.0.1.dist-info/WHEEL
logloglog-0.0.1.dist-info/METADATA
logloglog-0.0.1.dist-info/RECORD
